dms_patterns/__init__.py
dms_patterns/py.typed
dms_patterns/_jsii/__init__.py
dms_patterns/_jsii/dms-patterns@0.0.12.jsii.tgz
dms_patterns-0.0.12.dist-info/LICENSE
dms_patterns-0.0.12.dist-info/METADATA
dms_patterns-0.0.12.dist-info/WHEEL
dms_patterns-0.0.12.dist-info/top_level.txt
dms_patterns-0.0.12.dist-info/RECORD
